tellervo/exception.py
tellervo/utils.py
tellervo/__init__.py
tellervo_python-0.0.1.dist-info/top_level.txt
tellervo_python-0.0.1.dist-info/METADATA
tellervo_python-0.0.1.dist-info/RECORD
tellervo_python-0.0.1.dist-info/metadata.json
tellervo_python-0.0.1.dist-info/WHEEL
tellervo_python-0.0.1.dist-info/DESCRIPTION.rst
